README.md
setup.py
waitGPU.py
waitGPU.egg-info/PKG-INFO
waitGPU.egg-info/SOURCES.txt
waitGPU.egg-info/dependency_links.txt
waitGPU.egg-info/requires.txt
waitGPU.egg-info/top_level.txt