Metadata-Version: 1.0
Name: waitGPU
Version: 0.0.1
Summary: A small Python library that waits for GPU conditions to be satisfied, and then setting `CUDA_VISIBLE_DEVICES` to the qualifying GPU on multi-GPU systems.
Home-page: https://github.com/riceric22/waitGPU
Author: Eric Wong
Author-email: ericwong@cs.cmu.edu
License: Public Domain
Platform: any
